{"companySeoName":"aegis-limited","companyName":"AEGIS LIMITED","location":"","imageExist":"False","socialUrlMap":{"linkedin":null,"facebook":null,"twiter":null},"reviewQuestionAnswesSection":[{"sectionName":"Salary","sectionNameHi":null,"reviewQuestionAnswesViews":[{"QuestionText":"Is the salary as per market standard?","QuestionTextHi":null,"AnswerText":null,"AnswerTextHi":null,"totalAnswerCount":"74","answersView":[{"AnswerText":"Yes","AnswerTextHi":"हाँ","AnswerCount":"34"},{"AnswerText":"No","AnswerTextHi":"नहीं","AnswerCount":"40"}]},{"QuestionText":"Tell us about your last increment","QuestionTextHi":null,"AnswerText":null,"AnswerTextHi":null,"totalAnswerCount":"71","answersView":[{"AnswerText":"Less than 10%","AnswerTextHi":"10 से कम%","AnswerCount":"42"},{"AnswerText":"10-15%","AnswerTextHi":"10-15%","AnswerCount":"9"},{"AnswerText":"15-20%","AnswerTextHi":"15-20%","AnswerCount":"2"},{"AnswerText":"Not Eligible","AnswerTextHi":"पात्र नहीं है","AnswerCount":"18"}]}]},{"sectionName":"Work life balance","sectionNameHi":null,"reviewQuestionAnswesViews":[{"QuestionText":"How many hours you normally work in a day?","QuestionTextHi":null,"AnswerText":null,"AnswerTextHi":null,"totalAnswerCount":"0","answersView":[{"AnswerText":"5-6 Hours","AnswerTextHi":"5-6 घंटे","AnswerCount":"0"},{"AnswerText":"8-10 Hours","AnswerTextHi":"8-10 घंटे","AnswerCount":"0"},{"AnswerText":"10+ Hours","AnswerTextHi":"10+ घंटे","AnswerCount":"0"}]},{"QuestionText":"Does AEGIS LIMITED have a flexible working hours policy?","QuestionTextHi":null,"AnswerText":null,"AnswerTextHi":null,"totalAnswerCount":"0","answersView":[{"AnswerText":"Yes","AnswerTextHi":"हाँ","AnswerCount":"0"},{"AnswerText":"No","AnswerTextHi":"नहीं","AnswerCount":"0"},{"AnswerText":"Case to case basis","AnswerTextHi":"केस टू केस आधार","AnswerCount":"0"}]}]},{"sectionName":"Company culture","sectionNameHi":null,"reviewQuestionAnswesViews":[{"QuestionText":"How smart are your colleagues?","QuestionTextHi":null,"AnswerText":null,"AnswerTextHi":null,"totalAnswerCount":"74","answersView":[{"AnswerText":"Extremely smart","AnswerTextHi":"बेहद होशियार","AnswerCount":"23"},{"AnswerText":"Average","AnswerTextHi":"औसत","AnswerCount":"43"},{"AnswerText":"Below average","AnswerTextHi":"औसत से कम","AnswerCount":"8"}]},{"QuestionText":"How punctual are your co-workers?","QuestionTextHi":null,"AnswerText":null,"AnswerTextHi":null,"totalAnswerCount":"74","answersView":[{"AnswerText":"Always on time","AnswerTextHi":"हमेशा समय पर","AnswerCount":"27"},{"AnswerText":"Most of time","AnswerTextHi":"अधिकांश समय","AnswerCount":"41"},{"AnswerText":"Seldom on time","AnswerTextHi":"समय पर शायद ही कभी","AnswerCount":"6"}]},{"QuestionText":"How often do you have parties/offsites?","QuestionTextHi":null,"AnswerText":null,"AnswerTextHi":null,"totalAnswerCount":"73","answersView":[{"AnswerText":"Weekly","AnswerTextHi":"साप्ताहिक","AnswerCount":"3"},{"AnswerText":"Monthly","AnswerTextHi":"महीने के","AnswerCount":"9"},{"AnswerText":"Quarterly","AnswerTextHi":"त्रैमासिक","AnswerCount":"16"},{"AnswerText":"Yearly","AnswerTextHi":"सालाना","AnswerCount":"12"},{"AnswerText":"Managment doesn't believe in it","AnswerTextHi":"प्रबंधन इस पर विश्वास नहीं करता है","AnswerCount":"33"}]}]},{"sectionName":"Career growth","sectionNameHi":null,"reviewQuestionAnswesViews":[{"QuestionText":"How often do employees get promotions?","QuestionTextHi":null,"AnswerText":null,"AnswerTextHi":null,"totalAnswerCount":"73","answersView":[{"AnswerText":"Less than 1 year","AnswerTextHi":"एक वर्ष से कम","AnswerCount":"10"},{"AnswerText":"1-2 Years","AnswerTextHi":"1-2 साल","AnswerCount":"23"},{"AnswerText":"2-3 Years","AnswerTextHi":"2-3 साल","AnswerCount":"16"},{"AnswerText":"3+ Years","AnswerTextHi":"3+ साल","AnswerCount":"24"}]},{"QuestionText":"How many trainings do you attend every year?","QuestionTextHi":null,"AnswerText":null,"AnswerTextHi":null,"totalAnswerCount":"73","answersView":[{"AnswerText":"More than 6 times in a year","AnswerTextHi":"एक वर्ष में 6 बार से अधिक","AnswerCount":"17"},{"AnswerText":"3-5 times in a year","AnswerTextHi":"एक वर्ष में 3-5 बार","AnswerCount":"8"},{"AnswerText":"1-2 times in a year","AnswerTextHi":"एक वर्ष में 1-2 बार","AnswerCount":"16"},{"AnswerText":"No such programs","AnswerTextHi":"ऐसे कोई कार्यक्रम नहीं","AnswerCount":"32"}]}]}],"widgets":null,"companyVarient":["aegis","aegis tech limited","aegis technologies","aegis limited","aegis pvt ltd","aegis tech","aegis ltd essar group","aegis ltd"],"individualRatings":{"overAllRating":2.96,"salary":2.91,"workLife":3.11,"culture":3.1,"growth":2.7},"counts":{"mixedFeelCount":47,"notRecommendCount":48,"recommendCount":27},"companySalary":{"totalResults":45,"results":[{"salaryTitle":"Customer Care Executive/ Associate - Voice","salaryTitleHi":null,"employeeDesignation":"Customer Care Executive/ Associate - Voice","employeeDesignationHi":null,"cmpRating":2.96,"noRatedBy":43,"salaryMin":152233.0,"salaryMax":390033.0,"salaryMean":237402.0},{"salaryTitle":"Customer Care Executive/ Associate - Non Voice/ Web","salaryTitleHi":null,"employeeDesignation":"Customer Care Executive/ Associate - Non Voice/ Web","employeeDesignationHi":null,"cmpRating":2.96,"noRatedBy":41,"salaryMin":150400.0,"salaryMax":280900.0,"salaryMean":215921.0},{"salaryTitle":"System Administrator","salaryTitleHi":null,"employeeDesignation":"System Administrator","employeeDesignationHi":null,"cmpRating":2.96,"noRatedBy":30,"salaryMin":197850.0,"salaryMax":517600.0,"salaryMean":302831.0},{"salaryTitle":"Accountant/ Accounts Executive","salaryTitleHi":null,"employeeDesignation":"Accountant/ Accounts Executive","employeeDesignationHi":null,"cmpRating":2.96,"noRatedBy":28,"salaryMin":185750.0,"salaryMax":496800.0,"salaryMean":316024.0},{"salaryTitle":"Operations Manager","salaryTitleHi":null,"employeeDesignation":"Operations Manager","employeeDesignationHi":null,"cmpRating":2.96,"noRatedBy":21,"salaryMin":259700.0,"salaryMax":874650.0,"salaryMean":487838.0},{"salaryTitle":"HR Executive/ Officer","salaryTitleHi":null,"employeeDesignation":"HR Executive/ Officer","employeeDesignationHi":null,"cmpRating":2.96,"noRatedBy":20,"salaryMin":181900.0,"salaryMax":387400.0,"salaryMean":267632.0},{"salaryTitle":"Team Lead","salaryTitleHi":null,"employeeDesignation":"Team Lead","employeeDesignationHi":null,"cmpRating":2.96,"noRatedBy":20,"salaryMin":194700.0,"salaryMax":418950.0,"salaryMean":308616.0},{"salaryTitle":"Team Lead - Voice","salaryTitleHi":null,"employeeDesignation":"Team Lead - Voice","employeeDesignationHi":null,"cmpRating":2.96,"noRatedBy":20,"salaryMin":199800.0,"salaryMax":547900.0,"salaryMean":345242.0},{"salaryTitle":"HR Generalist","salaryTitleHi":null,"employeeDesignation":"HR Generalist","employeeDesignationHi":null,"cmpRating":2.96,"noRatedBy":17,"salaryMin":201000.0,"salaryMax":732350.0,"salaryMean":430046.0},{"salaryTitle":"Software Developer/ Programmer","salaryTitleHi":null,"employeeDesignation":"Software Developer/ Programmer","employeeDesignationHi":null,"cmpRating":2.96,"noRatedBy":15,"salaryMin":182633.0,"salaryMax":955466.0,"salaryMean":487320.0},{"salaryTitle":"Operations/ Process - Associate","salaryTitleHi":null,"employeeDesignation":"Operations/ Process - Associate","employeeDesignationHi":null,"cmpRating":2.96,"noRatedBy":14,"salaryMin":152866.0,"salaryMax":314133.0,"salaryMean":224007.0},{"salaryTitle":"System Engineer","salaryTitleHi":null,"employeeDesignation":"System Engineer","employeeDesignationHi":null,"cmpRating":2.96,"noRatedBy":12,"salaryMin":198866.0,"salaryMax":275266.0,"salaryMean":235723.0},{"salaryTitle":"Team Lead/ Tech Lead","salaryTitleHi":null,"employeeDesignation":"Team Lead/ Tech Lead","employeeDesignationHi":null,"cmpRating":2.96,"noRatedBy":12,"salaryMin":209700.0,"salaryMax":858533.0,"salaryMean":446287.0},{"salaryTitle":"Fresher","salaryTitleHi":null,"employeeDesignation":"Fresher","employeeDesignationHi":null,"cmpRating":2.96,"noRatedBy":12,"salaryMin":165500.0,"salaryMax":267433.0,"salaryMean":218724.0},{"salaryTitle":"MIS Executive","salaryTitleHi":null,"employeeDesignation":"MIS Executive","employeeDesignationHi":null,"cmpRating":2.96,"noRatedBy":11,"salaryMin":189700.0,"salaryMax":490200.0,"salaryMean":362773.0},{"salaryTitle":"Project Leader/ Project Manager","salaryTitleHi":null,"employeeDesignation":"Project Leader/ Project Manager","employeeDesignationHi":null,"cmpRating":2.96,"noRatedBy":10,"salaryMin":216866.0,"salaryMax":962366.0,"salaryMean":544374.0},{"salaryTitle":"Quality - Coach/ Analyst","salaryTitleHi":null,"employeeDesignation":"Quality - Coach/ Analyst","employeeDesignationHi":null,"cmpRating":2.96,"noRatedBy":10,"salaryMin":213433.0,"salaryMax":362166.0,"salaryMean":290315.0},{"salaryTitle":"Technical Support Associate (Voice)","salaryTitleHi":null,"employeeDesignation":"Technical Support Associate (Voice)","employeeDesignationHi":null,"cmpRating":2.96,"noRatedBy":10,"salaryMin":189400.0,"salaryMax":307933.0,"salaryMean":236238.0},{"salaryTitle":"Training & Development - Manager","salaryTitleHi":null,"employeeDesignation":"Training & Development - Manager","employeeDesignationHi":null,"cmpRating":2.96,"noRatedBy":10,"salaryMin":566366.0,"salaryMax":856200.0,"salaryMean":735844.0},{"salaryTitle":"Database Analyst/ Programmer","salaryTitleHi":null,"employeeDesignation":"Database Analyst/ Programmer","employeeDesignationHi":null,"cmpRating":2.96,"noRatedBy":9,"salaryMin":180266.0,"salaryMax":470200.0,"salaryMean":343564.0},{"salaryTitle":"Other Telecom - Operations/ Support","salaryTitleHi":null,"employeeDesignation":"Other Telecom - Operations/ Support","employeeDesignationHi":null,"cmpRating":2.96,"noRatedBy":8,"salaryMin":189800.0,"salaryMax":380500.0,"salaryMean":272062.0},{"salaryTitle":"Technical Support Engineer","salaryTitleHi":null,"employeeDesignation":"Technical Support Engineer","employeeDesignationHi":null,"cmpRating":2.96,"noRatedBy":8,"salaryMin":189600.0,"salaryMax":580400.0,"salaryMean":326937.0},{"salaryTitle":"Technical Support Manager","salaryTitleHi":null,"employeeDesignation":"Technical Support Manager","employeeDesignationHi":null,"cmpRating":2.96,"noRatedBy":8,"salaryMin":237700.0,"salaryMax":900200.0,"salaryMean":573289.0},{"salaryTitle":"Process Flow/ Work Flow Analyst","salaryTitleHi":null,"employeeDesignation":"Process Flow/ Work Flow Analyst","employeeDesignationHi":null,"cmpRating":2.96,"noRatedBy":7,"salaryMin":239200.0,"salaryMax":525700.0,"salaryMean":387644.0},{"salaryTitle":"Team Lead - Non Voice/ Web","salaryTitleHi":null,"employeeDesignation":"Team Lead - Non Voice/ Web","employeeDesignationHi":null,"cmpRating":2.96,"noRatedBy":7,"salaryMin":287900.0,"salaryMax":535500.0,"salaryMean":413655.0},{"salaryTitle":"HR Lead/ Territory HR Lead","salaryTitleHi":null,"employeeDesignation":"HR Lead/ Territory HR Lead","employeeDesignationHi":null,"cmpRating":2.96,"noRatedBy":6,"salaryMin":274700.0,"salaryMax":425100.0,"salaryMean":370925.0},{"salaryTitle":"Network Administrator","salaryTitleHi":null,"employeeDesignation":"Network Administrator","employeeDesignationHi":null,"cmpRating":2.96,"noRatedBy":6,"salaryMin":179200.0,"salaryMax":810500.0,"salaryMean":428735.0},{"salaryTitle":"Operations/ Support Head","salaryTitleHi":null,"employeeDesignation":"Operations/ Support Head","employeeDesignationHi":null,"cmpRating":2.96,"noRatedBy":6,"salaryMin":158600.0,"salaryMax":643200.0,"salaryMean":348077.0},{"salaryTitle":"Other IT Software - ERP, CRM","salaryTitleHi":null,"employeeDesignation":"Other IT Software - ERP, CRM","employeeDesignationHi":null,"cmpRating":2.96,"noRatedBy":6,"salaryMin":459800.0,"salaryMax":838900.0,"salaryMean":644524.0},{"salaryTitle":"Quality - Team Lead","salaryTitleHi":null,"employeeDesignation":"Quality - Team Lead","employeeDesignationHi":null,"cmpRating":2.96,"noRatedBy":6,"salaryMin":313000.0,"salaryMax":512700.0,"salaryMean":392722.0},{"salaryTitle":"Recruitment - Executive/ Officer","salaryTitleHi":null,"employeeDesignation":"Recruitment - Executive/ Officer","employeeDesignationHi":null,"cmpRating":2.96,"noRatedBy":6,"salaryMin":244400.0,"salaryMax":382700.0,"salaryMean":309256.0},{"salaryTitle":"Recruitment - Manager","salaryTitleHi":null,"employeeDesignation":"Recruitment - Manager","employeeDesignationHi":null,"cmpRating":2.96,"noRatedBy":6,"salaryMin":419400.0,"salaryMax":712800.0,"salaryMean":557524.0},{"salaryTitle":"Trainer - Technical/ Process","salaryTitleHi":null,"employeeDesignation":"Trainer - Technical/ Process","employeeDesignationHi":null,"cmpRating":2.96,"noRatedBy":6,"salaryMin":170300.0,"salaryMax":408400.0,"salaryMean":272080.0},{"salaryTitle":"ERP, CRM Functional Consultant","salaryTitleHi":null,"employeeDesignation":"ERP, CRM Functional Consultant","employeeDesignationHi":null,"cmpRating":2.96,"noRatedBy":5,"salaryMin":629400.0,"salaryMax":1089800.0,"salaryMean":857646.0},{"salaryTitle":"Financial Accountant","salaryTitleHi":null,"employeeDesignation":"Financial Accountant","employeeDesignationHi":null,"cmpRating":2.96,"noRatedBy":5,"salaryMin":244300.0,"salaryMax":480400.0,"salaryMean":355019.0},{"salaryTitle":"Floor Supervisor/ Manager - Voice","salaryTitleHi":null,"employeeDesignation":"Floor Supervisor/ Manager - Voice","employeeDesignationHi":null,"cmpRating":2.96,"noRatedBy":5,"salaryMin":203800.0,"salaryMax":503900.0,"salaryMean":343059.0},{"salaryTitle":"HR Manager","salaryTitleHi":null,"employeeDesignation":"HR Manager","employeeDesignationHi":null,"cmpRating":2.96,"noRatedBy":5,"salaryMin":712400.0,"salaryMax":979500.0,"salaryMean":835002.0},{"salaryTitle":"Operations/ Process - Manager","salaryTitleHi":null,"employeeDesignation":"Operations/ Process - Manager","employeeDesignationHi":null,"cmpRating":2.96,"noRatedBy":5,"salaryMin":461800.0,"salaryMax":1025500.0,"salaryMean":703661.0},{"salaryTitle":"Other Call Centre/ Operations/ Customer Service","salaryTitleHi":null,"employeeDesignation":"Other Call Centre/ Operations/ Customer Service","employeeDesignationHi":null,"cmpRating":2.96,"noRatedBy":5,"salaryMin":181800.0,"salaryMax":1060400.0,"salaryMean":545882.0},{"salaryTitle":"Other IT Hardware - Networking","salaryTitleHi":null,"employeeDesignation":"Other IT Hardware - Networking","employeeDesignationHi":null,"cmpRating":2.96,"noRatedBy":5,"salaryMin":169900.0,"salaryMax":214300.0,"salaryMean":193428.0},{"salaryTitle":"Process Manager - Voice","salaryTitleHi":null,"employeeDesignation":"Process Manager - Voice","employeeDesignationHi":null,"cmpRating":2.96,"noRatedBy":5,"salaryMin":401500.0,"salaryMax":790400.0,"salaryMean":616884.0},{"salaryTitle":"Sales Executive/ Officer","salaryTitleHi":null,"employeeDesignation":"Sales Executive/ Officer","employeeDesignationHi":null,"cmpRating":2.96,"noRatedBy":5,"salaryMin":164400.0,"salaryMax":213300.0,"salaryMean":187076.0},{"salaryTitle":"Sales/ Business Development Manager","salaryTitleHi":null,"employeeDesignation":"Sales/ Business Development Manager","employeeDesignationHi":null,"cmpRating":2.96,"noRatedBy":5,"salaryMin":181800.0,"salaryMax":900800.0,"salaryMean":572841.0},{"salaryTitle":"Switching/ Router Engineer","salaryTitleHi":null,"employeeDesignation":"Switching/ Router Engineer","employeeDesignationHi":null,"cmpRating":2.96,"noRatedBy":5,"salaryMin":199800.0,"salaryMax":250600.0,"salaryMean":220057.0},{"salaryTitle":"Trainer","salaryTitleHi":null,"employeeDesignation":"Trainer","employeeDesignationHi":null,"cmpRating":2.96,"noRatedBy":5,"salaryMin":183900.0,"salaryMax":225200.0,"salaryMean":203825.0}]},"getCompanyProsCons":{"reviewCount":142,"pros":[{"count":38,"name":"People/Colleagues","nameHi":null},{"count":22,"name":"Employee Friendliness & benefits","nameHi":null},{"count":17,"name":"Work Environment","nameHi":null},{"count":16,"name":"Work-Life Balance","nameHi":null},{"count":12,"name":"Quality of Work","nameHi":null}],"cons":[{"count":36,"name":"Salary","nameHi":null},{"count":23,"name":"Average Yearly Appraisal","nameHi":null},{"count":18,"name":"Limited Career Growth Opportunities","nameHi":null},{"count":16,"name":"No Work from Home","nameHi":null},{"count":14,"name":"No Cab & Transport Facility","nameHi":null}]},"companyInfo":{"Founded":null,"Founder":null,"FounderHi":null,"Employees":null,"Turnover":null,"Headquarters":null,"HeadquartersHi":null,"Industry":[{"slug":"bpos","name":null,"nameHi":null},{"slug":"kpos","name":null,"nameHi":null},{"slug":"lpos","name":null,"nameHi":null},{"slug":"ites","name":null,"nameHi":null},{"slug":"transcription","name":null,"nameHi":null}],"Website":null},"googleCompanyResponse":{"itemListElement":[{"resultScore":1659.424560546875,"result":{"url":"http://www.aegisglobal.com/","detailedDescription":null,"image":null,"description":"Company","descriptionHi":null,"name":"Aegis Limited","nameHi":null,"imageName":null}}]},"dateCreated":"2021-06-14T16:33:26.231Z","dateModified":"2021-06-14T16:33:26.231Z","id":27926,"slug":"aegis-limited","recommendations":[{"companySeoName":"provana","companyName":"Provana","imageExist":"False","Industry":[{"name":"BPOs","slug":"bpos"},{"name":" KPOs","slug":"kpos"},{"name":" LPOs","slug":"lpos"},{"name":" ITES","slug":"ites"},{"name":" Transcription","slug":"transcription"}],"imageUrl":"45653.png","total":0},{"companySeoName":"prestine-solutions-llp","companyName":"Prestine Solutions LLP","imageExist":"False","Industry":[{"name":"BPOs","slug":"bpos"},{"name":" KPOs","slug":"kpos"},{"name":" LPOs","slug":"lpos"},{"name":" ITES","slug":"ites"},{"name":" Transcription","slug":"transcription"}],"imageUrl":"45147.png","total":0},{"companySeoName":"aiges-limited","companyName":"aiges limited","imageExist":"False","Industry":[{"name":"BPOs","slug":"bpos"},{"name":" KPOs","slug":"kpos"},{"name":" LPOs","slug":"lpos"},{"name":" ITES","slug":"ites"},{"name":" Transcription","slug":"transcription"}],"imageUrl":"44382.png","total":0},{"companySeoName":"karmic-lifesciences","companyName":"KARMIC LIFESCIENCES","imageExist":"False","Industry":[{"name":"BPOs","slug":"bpos"},{"name":" KPOs","slug":"kpos"},{"name":" LPOs","slug":"lpos"},{"name":" ITES","slug":"ites"},{"name":" Transcription","slug":"transcription"}],"imageUrl":"44091.png","total":0},{"companySeoName":"kankei-relationship","companyName":"KANKEI RELATIONSHIP","imageExist":"False","Industry":[{"name":"BPOs","slug":"bpos"},{"name":" KPOs","slug":"kpos"},{"name":" LPOs","slug":"lpos"},{"name":" ITES","slug":"ites"},{"name":" Transcription","slug":"transcription"}],"imageUrl":"44076.png","total":0},{"companySeoName":"xplore-tech","companyName":"XPLORE TECH","imageExist":"False","Industry":[{"name":"BPOs","slug":"bpos"},{"name":" KPOs","slug":"kpos"},{"name":" LPOs","slug":"lpos"},{"name":" ITES","slug":"ites"},{"name":" Transcription","slug":"transcription"}],"imageUrl":"43652.png","total":0},{"companySeoName":"xpitax-solutions-pvt-ltd","companyName":"XPITAX SOLUTIONS PVT LTD","imageExist":"False","Industry":[{"name":"BPOs","slug":"bpos"},{"name":" KPOs","slug":"kpos"},{"name":" LPOs","slug":"lpos"},{"name":" ITES","slug":"ites"},{"name":" Transcription","slug":"transcription"}],"imageUrl":"43644.png","total":0},{"companySeoName":"i2c-world","companyName":"I2C WORLD","imageExist":"False","Industry":[{"name":"BPOs","slug":"bpos"},{"name":" KPOs","slug":"kpos"},{"name":" LPOs","slug":"lpos"},{"name":" ITES","slug":"ites"},{"name":" Transcription","slug":"transcription"}],"imageUrl":"43469.png","total":0},{"companySeoName":"i2i","companyName":"I2I","imageExist":"False","Industry":[{"name":"BPOs","slug":"bpos"},{"name":" KPOs","slug":"kpos"},{"name":" LPOs","slug":"lpos"},{"name":" ITES","slug":"ites"},{"name":" Transcription","slug":"transcription"}],"imageUrl":"43465.png","total":0},{"companySeoName":"wings-customer-care","companyName":"WINGS CUSTOMER CARE","imageExist":"False","Industry":[{"name":"BPOs","slug":"bpos"},{"name":" KPOs","slug":"kpos"},{"name":" LPOs","slug":"lpos"},{"name":" ITES","slug":"ites"},{"name":" Transcription","slug":"transcription"}],"imageUrl":"43303.png","total":0},{"companySeoName":"ibsn","companyName":"IBSN","imageExist":"False","Industry":[{"name":"BPOs","slug":"bpos"},{"name":" KPOs","slug":"kpos"},{"name":" LPOs","slug":"lpos"},{"name":" ITES","slug":"ites"},{"name":" Transcription","slug":"transcription"}],"imageUrl":"43053.png","total":0},{"companySeoName":"akash-computers","companyName":"AKASH COMPUTERS","imageExist":"False","Industry":[{"name":"BPOs","slug":"bpos"},{"name":" KPOs","slug":"kpos"},{"name":" LPOs","slug":"lpos"},{"name":" ITES","slug":"ites"},{"name":" Transcription","slug":"transcription"}],"imageUrl":"42963.png","total":0}],"imageUrl":"27926.png"}