[{"id":18343,"title":"वेस क्रेवन की नई दुःस्वप्न","year":"1994","released":"14 Oct 1994","runtime":"112 min","genre":[{"name":"कपोल कल्पित","slug":"fantasy"},{"name":"डरावनी","slug":"horror"},{"name":"रहस्य","slug":"mystery"},{"name":"थ्रिलर","slug":"thriller"}],"actors":[{"name":"जेफ डेविस","slug":"jeff-davis"},{"name":"हीदर लैंगकैंप","slug":"heather-langenkamp"},{"name":"मोको ह्यूजेस","slug":"miko-hughes"},{"name":"मैट विंस्टन","slug":"matt-winston"}],"slug":"wes-cravens-new-nightmare","imageUrl":"att0111686z.jpg","total":26},{"id":18294,"title":"एल्म स्ट्रीट 2 पर एक बुरा सपना: फ्रेडी का बदला","year":"1985","released":"01 Nov 1985","runtime":"87 min","genre":[{"name":"डरावनी","slug":"horror"}],"actors":[{"name":"पैटन को चिह्नित करें","slug":"mark-patton"},{"name":"किम मायर्स","slug":"kim-myers"},{"name":"रॉबर्ट रुसलर","slug":"robert-rusler"},{"name":"क्लू गुलगर","slug":"clu-gulager"}],"slug":"a-nightmare-on-elm-street-2-freddys-revenge","imageUrl":"att0089686z.jpg","total":26},{"id":18225,"title":"एल्म स्ट्रीट 3 पर एक बुरा सपना: ड्रीम वारियर्स","year":"1987","released":"27 Feb 1987","runtime":"96 min","genre":[{"name":"कपोल कल्पित","slug":"fantasy"},{"name":"डरावनी","slug":"horror"}],"actors":[{"name":"हीदर लैंगकैंप","slug":"heather-langenkamp"},{"name":"क्रेग वासन","slug":"craig-wasson"},{"name":"पेट्रीसिया अर्क्वेट","slug":"patricia-arquette"},{"name":"रॉबर्ट एंगलंड","slug":"robert-englund"}],"slug":"a-nightmare-on-elm-street-3-dream-warriors","imageUrl":"att0093629z.jpg","total":26},{"id":18198,"title":"एल्म सड़क पर बुरा सपना","year":"2010","released":"30 Apr 2010","runtime":"95 min","genre":[{"name":"अपराध","slug":"crime"},{"name":"नाटक","slug":"drama"},{"name":"डरावनी","slug":"horror"},{"name":"रहस्य","slug":"mystery"}],"actors":[{"name":"जैकी अर्ले हेली","slug":"jackie-earle-haley"},{"name":"काइल गैलर","slug":"kyle-gallner"},{"name":"रूनी मारा","slug":"rooney-mara"},{"name":"केटी कैसिडी","slug":"katie-cassidy"}],"slug":"a-nightmare-on-elm-street","imageUrl":"att1179056z.jpg","total":26},{"id":18184,"title":"बाईं तरफ का आखिरी घर","year":"1972","released":"30 Aug 1972","runtime":"84 min","genre":[{"name":"डरावनी","slug":"horror"},{"name":"थ्रिलर","slug":"thriller"}],"actors":[{"name":"सैंड्रा पीबॉडी","slug":"sandra-peabody"},{"name":"लुसी ग्रन्थम","slug":"lucy-grantham"},{"name":"डेविड हेस","slug":"david-hess"},{"name":"फ्रेड जे, लिंकन","slug":"fred-j.-lincoln"}],"slug":"the-last-house-on-the-left","imageUrl":"att0068833z.jpg","total":26},{"id":18130,"title":"बाईं तरफ का आखिरी घर","year":"2009","released":"13 Mar 2009","runtime":"110 min","genre":[{"name":"डरावनी","slug":"horror"},{"name":"थ्रिलर","slug":"thriller"}],"actors":[{"name":"गैरेट डिलाहंट","slug":"garret-dillahunt"},{"name":"माइकल बोवेन","slug":"michael-bowen"},{"name":"जोश कोक्सक्स","slug":"josh-coxx"},{"name":"रिकी लिंडोम","slug":"riki-lindhome"}],"slug":"the-last-house-on-the-left","imageUrl":"att0844708z.jpg","total":26},{"id":18098,"title":"फ्रेडी बनाम, जेसन","year":"2003","released":"15 Aug 2003","runtime":"97 min","genre":[{"name":"कार्य","slug":"action"},{"name":"डरावनी","slug":"horror"}],"actors":[{"name":"रॉबर्ट एंगलंड","slug":"robert-englund"},{"name":"केन किरिंजर","slug":"ken-kirzinger"},{"name":"मोनिका कीना","slug":"monica-keena"},{"name":"जेसन रिटर","slug":"jason-ritter"}],"slug":"freddy-vs.-jason","imageUrl":"att0329101z.jpg","total":26},{"id":18072,"title":"पहाड़ियों की आँखें है","year":"2006","released":"10 Mar 2006","runtime":"107 min","genre":[{"name":"डरावनी","slug":"horror"},{"name":"थ्रिलर","slug":"thriller"}],"actors":[{"name":"मैक्सिमे जिफ़र्ड","slug":"maxime-giffard"},{"name":"माइकल बेली स्मिथ","slug":"michael-bailey-smith"},{"name":"टॉम बोवर","slug":"tom-bower"},{"name":"टेड लेविन","slug":"ted-levine"}],"slug":"the-hills-have-eyes","imageUrl":"att0454841z.jpg","total":26},{"id":17995,"title":"एल्म सड़क पर बुरा सपना","year":"1984","released":"16 Nov 1984","runtime":"91 min","genre":[{"name":"डरावनी","slug":"horror"}],"actors":[{"name":"जॉन सेक्सन","slug":"john-saxon"},{"name":"रोने ब्लेकले","slug":"ronee-blakley"},{"name":"हीदर लैंगकैंप","slug":"heather-langenkamp"},{"name":"अमांडा Wyss","slug":"amanda-wyss"}],"slug":"a-nightmare-on-elm-street","imageUrl":"att0087800z.jpg","total":26},{"id":11197,"title":"नाड़ी","year":"2006","released":"11 Aug 2006","runtime":"90 min","genre":[{"name":"डरावनी","slug":"horror"},{"name":"विज्ञान-कथा","slug":"sci-fi"}],"actors":[{"name":"क्रिस्टन बेल","slug":"kristen-bell"},{"name":"इयन सोमरहॉल्डर","slug":"ian-somerhalder"},{"name":"क्रिस्टीना मिलियन","slug":"christina-milian"},{"name":"रिक गोंजालेज","slug":"rick-gonzalez"}],"slug":"pulse","imageUrl":"att0454919z.jpg","total":26},{"id":11054,"title":"दलदल की चीज","year":"1982","released":"19 Feb 1982","runtime":"91 min","genre":[{"name":"डरावनी","slug":"horror"},{"name":"विज्ञान-कथा","slug":"sci-fi"}],"actors":[{"name":"लुइस जार्डन","slug":"louis-jourdan"},{"name":"एड्रिएन बारब्यू","slug":"adrienne-barbeau"},{"name":"रे समझदार","slug":"ray-wise"},{"name":"डेविड हेस","slug":"david-hess"}],"slug":"swamp-thing","imageUrl":"att0084745z.jpg","total":26},{"id":4710,"title":"घिनौना आदमी","year":"1989","released":"27 Oct 1989","runtime":"109 min","genre":[{"name":"कॉमेडी","slug":"comedy"},{"name":"डरावनी","slug":"horror"},{"name":"थ्रिलर","slug":"thriller"}],"actors":[{"name":"मिच पिलाग्गी","slug":"mitch-pileggi"},{"name":"जॉन टेश","slug":"john-tesh"},{"name":"हीदर लैंगकैंप","slug":"heather-langenkamp"},{"name":"पीटर बर्ग","slug":"peter-berg"}],"slug":"shocker","imageUrl":"att0098320z.jpg","total":26}]