[{"id":34264,"title":"High-Ballin'","year":"1978","released":"26 May 1978","runtime":"97 min","genre":[{"name":"Action","slug":"action"},{"name":"Drama","slug":"drama"}],"actors":[{"name":"Peter Fonda","slug":"peter-fonda"},{"name":"Jerry Reed","slug":"jerry-reed"},{"name":"Helen Shaver","slug":"helen-shaver"},{"name":"Chris Wiggins","slug":"chris-wiggins"}],"slug":"high-ballin","imageUrl":"att0077679z.jpg","total":2},{"id":16791,"title":"Welcome to Blood City","year":"1977","released":"02 Mar 1984","runtime":"96 min","genre":[{"name":"Drama","slug":"drama"},{"name":"Mystery","slug":"mystery"},{"name":"Sci-Fi","slug":"sci-fi"},{"name":"Thriller","slug":"thriller"},{"name":"Western","slug":"western"}],"actors":[{"name":"Jack Palance","slug":"jack-palance"},{"name":"Keir Dullea","slug":"keir-dullea"},{"name":"Samantha Eggar","slug":"samantha-eggar"},{"name":"Barry Morse","slug":"barry-morse"}],"slug":"welcome-to-blood-city","imageUrl":"att0076909z.jpg","total":2}]