[{"companySeoName":"itbp-force","companyName":"ITBP FORCE","imageExist":"False","Industry":[{"name":"Other Industry","slug":"other-industry"}],"imageUrl":"34943.png","total":44860},{"companySeoName":"it-point","companyName":"IT POINT","imageExist":"False","Industry":[{"name":"Education","slug":"education"},{"name":" Training Institutes & Academic Research","slug":"training-institutes-academic-research"}],"imageUrl":"34945.png","total":44860},{"companySeoName":"itc-india-ltd","companyName":"ITC INDIA LTD","imageExist":"False","Industry":[{"name":"Cement","slug":"cement"},{"name":" Building Materials & Construction Equipment","slug":"building-materials-construction-equipment"}],"imageUrl":"34946.png","total":44860},{"companySeoName":"it-hardware","companyName":"IT HARDWARE","imageExist":"False","Industry":[{"name":"Consumer Goods - Durables","slug":"consumer-goods-durables"}],"imageUrl":"34947.png","total":44860},{"companySeoName":"itc-wills-lifestyle","companyName":"ITC WILLS LIFESTYLE","imageExist":"False","Industry":[{"name":"Retail","slug":"retail"},{"name":" Shops","slug":"shops"},{"name":" Malls","slug":"malls"}],"imageUrl":"34948.png","total":44860},{"companySeoName":"itg-telematics-pvt-ltd","companyName":"ITG TELEMATICS PVT.LTD.","imageExist":"False","Industry":[{"name":"Construction","slug":"construction"},{"name":" Interiors & Real Estate Services","slug":"interiors-real-estate-services"}],"imageUrl":"34949.png","total":44860},{"companySeoName":"itm-group-of-institutions","companyName":"ITM GROUP OF INSTITUTIONS","imageExist":"False","Industry":[{"name":"Education","slug":"education"},{"name":" Training Institutes & Academic Research","slug":"training-institutes-academic-research"}],"imageUrl":"34950.png","total":44860},{"companySeoName":"iterate-india-private-limited","companyName":"ITERATE INDIA PRIVATE LIMITED","imageExist":"False","Industry":[{"name":"Technology (IT","slug":"technology-it"},{"name":" Telecom","slug":"telecom"},{"name":" Dot Com etc)","slug":"dot-com-etc"}],"imageUrl":"34952.png","total":44860},{"companySeoName":"its","companyName":"ITS","imageExist":"False","Industry":[{"name":"Other Industry","slug":"other-industry"}],"imageUrl":"34953.png","total":44860},{"companySeoName":"itrix-technology","companyName":"ITRIX TECHNOLOGY","imageExist":"False","Industry":[{"name":"Technology (IT","slug":"technology-it"},{"name":" Telecom","slug":"telecom"},{"name":" Dot Com etc)","slug":"dot-com-etc"}],"imageUrl":"34954.png","total":44860},{"companySeoName":"itc-foods-ltd","companyName":"ITC FOODS LTD","imageExist":"False","Industry":[{"name":"Consumer Goods - FMCG","slug":"consumer-goods-fmcg"}],"imageUrl":"34955.png","total":44860},{"companySeoName":"iti-financial-services-ltd","companyName":"ITI FINANCIAL SERVICES LTD","imageExist":"False","Industry":[{"name":"Banking","slug":"banking"},{"name":" Financial Services & Insurance","slug":"financial-services-insurance"}],"imageUrl":"34958.png","total":44860}]