[{"id":16681,"title":"वे हमारे बीच हैं","year":"2004","released":"17 Jul 2004","runtime":"99 min","genre":[{"name":"विज्ञान-कथा","slug":"sci-fi"},{"name":"थ्रिलर","slug":"thriller"}],"actors":[{"name":"एलिसन ईस्टवुड","slug":"alison-eastwood"},{"name":"माइकल ऑर ह्यूजेस","slug":"michael-orr-hughes"},{"name":"ऐनी अप्रा","slug":"anne-apra"},{"name":"लेसी बीमन","slug":"lacey-beeman"}],"slug":"they-are-among-us","imageUrl":"att0417191z.jpg","total":12007},{"id":16677,"title":"जाओ / मत जाओ","year":"2020","released":"01 Feb 2020","runtime":"95 min","genre":[{"name":"नाटक","slug":"drama"},{"name":"रहस्य","slug":"mystery"},{"name":"विज्ञान-कथा","slug":"sci-fi"},{"name":"थ्रिलर","slug":"thriller"}],"actors":[{"name":"एलेक्स कन्नप","slug":"alex-knapp"},{"name":"ओलिविया लुकर्डी","slug":"olivia-luccardi"},{"name":"नोर डेविस","slug":"nore-davis"},{"name":"थॉमस Essig","slug":"thomas-essig"}],"slug":"godont-go","imageUrl":"att8997082z.jpg","total":12007},{"id":16675,"title":"शिकार","year":"2006","released":"11 Dec 2006","runtime":"90 min","genre":[{"name":"डरावनी","slug":"horror"},{"name":"विज्ञान-कथा","slug":"sci-fi"},{"name":"थ्रिलर","slug":"thriller"}],"actors":[{"name":"जो माइकल बर्क","slug":"joe-michael-burke"},{"name":"क्लिफ डे यंग","slug":"cliff-de-young"},{"name":"रॉबर्ट रुसलर","slug":"robert-rusler"},{"name":"मिशेल बर्न्स","slug":"mitchell-burns"}],"slug":"the-hunt","imageUrl":"att0454843z.jpg","total":12007},{"id":16671,"title":"सील गश्ती","year":"2014","released":"06 Sep 2016","runtime":"80 min","genre":[{"name":"कार्य","slug":"action"},{"name":"विज्ञान-कथा","slug":"sci-fi"},{"name":"थ्रिलर","slug":"thriller"}],"actors":[{"name":"रिच मैकडॉनल्ड्स","slug":"rich-mcdonald"},{"name":"क्रिस्टीना अनापौ","slug":"kristina-anapau"},{"name":"जोशुआ सेंट, जेम्स","slug":"joshua-st.-james"},{"name":"एंजेल मैककॉर्ड","slug":"angel-mccord"}],"slug":"seal-patrol","imageUrl":"att2078549z.jpg","total":12007},{"id":16669,"title":"रेप्टिसॉरस","year":"2009","released":"10 Jun 2009","runtime":"81 min","genre":[{"name":"कार्य","slug":"action"},{"name":"साहसिक","slug":"adventure"},{"name":"कॉमेडी","slug":"comedy"},{"name":"डरावनी","slug":"horror"},{"name":"विज्ञान-कथा","slug":"sci-fi"},{"name":"थ्रिलर","slug":"thriller"}],"actors":[{"name":"गिल जेरार्ड","slug":"gil-gerard"},{"name":"बर्नार्ड फ्रेडरिक","slug":"bernard-fredericks"},{"name":"माइकल गैल्वेज","slug":"michael-galvez"},{"name":"एरिक फिशर","slug":"eric-fischer"}],"slug":"reptisaurus","imageUrl":"att1277731z.jpg","total":12007},{"id":16666,"title":"प्लेग","year":"1979","released":"26 Jan 1979","runtime":"88 min","genre":[{"name":"विज्ञान-कथा","slug":"sci-fi"},{"name":"नाटक","slug":"drama"},{"name":"थ्रिलर","slug":"thriller"}],"actors":[{"name":"डैनियल पिलोन","slug":"daniel-pilon"},{"name":"केट रीड","slug":"kate-reid"},{"name":"सेलाइन लोमेज़","slug":"celine-lomez"},{"name":"माइकल जे, रेनॉल्ड्स","slug":"michael-j.-reynolds"}],"slug":"plague","imageUrl":"att0078088z.jpg","total":12007},{"id":16662,"title":"नियंत्रण कारक","year":"2003","released":"18 Jan 2003","runtime":"84 min","genre":[{"name":"कार्य","slug":"action"},{"name":"विज्ञान-कथा","slug":"sci-fi"},{"name":"थ्रिलर","slug":"thriller"},{"name":"रहस्य","slug":"mystery"}],"actors":[{"name":"एडम बाल्डविन","slug":"adam-baldwin"},{"name":"एलिजाबेथ बर्कले","slug":"elizabeth-berkley"},{"name":"टोनी टोड","slug":"tony-todd"},{"name":"कॉनराड डन","slug":"conrad-dunn"}],"slug":"control-factor","imageUrl":"att0330171z.jpg","total":12007},{"id":16656,"title":"रेड ब्लडेड अमेरिकन गर्ल","year":"1990","released":"03 Jan 1997","runtime":"89 min","genre":[{"name":"कॉमेडी","slug":"comedy"},{"name":"डरावनी","slug":"horror"},{"name":"विज्ञान-कथा","slug":"sci-fi"},{"name":"थ्रिलर","slug":"thriller"}],"actors":[{"name":"एंड्रयू स्टीवंस","slug":"andrew-stevens"},{"name":"हीदर थॉमस","slug":"heather-thomas"},{"name":"क्रिस्टोफर प्लमर","slug":"christopher-plummer"},{"name":"किम कोट्स","slug":"kim-coates"}],"slug":"red-blooded-american-girl","imageUrl":"att0100466z.jpg","total":12007},{"id":16643,"title":"डार्क ब्रीड","year":"1996","released":"18 Dec 2003","runtime":"104 min","genre":[{"name":"कार्य","slug":"action"},{"name":"डरावनी","slug":"horror"},{"name":"विज्ञान-कथा","slug":"sci-fi"},{"name":"थ्रिलर","slug":"thriller"}],"actors":[{"name":"जैक स्कालिया","slug":"jack-scalia"},{"name":"सिंडी अंबुहाल","slug":"cindy-ambuehl"},{"name":"जोनाथन बैंक","slug":"jonathan-banks"},{"name":"ग्रेग ब्रेज़ल","slug":"gregg-brazzel"}],"slug":"dark-breed","imageUrl":"att0116026z.jpg","total":12007},{"id":16640,"title":"कुछ भी नहीं सच में होता है","year":"2018","released":"02 May 2018","runtime":"101 min","genre":[{"name":"कॉमेडी","slug":"comedy"},{"name":"विज्ञान-कथा","slug":"sci-fi"},{"name":"थ्रिलर","slug":"thriller"}],"actors":[{"name":"बॉबी डॉर्नबोस","slug":"bobby-dornbos"},{"name":"एडम एडवर्ड्स","slug":"adam-edwards"},{"name":"कम फ्रैंकलिन","slug":"kam-franklin"},{"name":"जोसेफ ग्राहम","slug":"joseph-graham"}],"slug":"nothing-really-happens","imageUrl":"att7297336z.jpg","total":12007},{"id":16639,"title":"कारण के लिए","year":"2000","released":"17 Dec 2002","runtime":"100 min","genre":[{"name":"कार्य","slug":"action"},{"name":"साहसिक","slug":"adventure"},{"name":"नाटक","slug":"drama"},{"name":"कपोल कल्पित","slug":"fantasy"},{"name":"विज्ञान-कथा","slug":"sci-fi"},{"name":"थ्रिलर","slug":"thriller"}],"actors":[{"name":"डीन कैन","slug":"dean-cain"},{"name":"थॉमस इयान ग्रिफिथ","slug":"thomas-ian-griffith"},{"name":"जस्टिन व्हालिन","slug":"justin-whalin"},{"name":"जोड़ी बियांका समझदार","slug":"jodi-bianca-wise"}],"slug":"for-the-cause","imageUrl":"att0113092z.jpg","total":12007},{"id":16635,"title":"भ्रष्टाचार किया हुआ","year":"2010","released":"07 May 2010","runtime":"76 min","genre":[{"name":"डरावनी","slug":"horror"},{"name":"विज्ञान-कथा","slug":"sci-fi"},{"name":"थ्रिलर","slug":"thriller"}],"actors":[{"name":"कालेब इयान मोरले फिशर","slug":"caleb-ian-morley-fischer"},{"name":"अनुज सारस्वत","slug":"anuj-saraswat"},{"name":"केल्टाई स्क्वायर्स","slug":"keltie-squires"},{"name":"जेरेमी हुक","slug":"jeremy-hook"}],"slug":"the-corrupted","imageUrl":"att1674197z.jpg","total":12007}]