[{"id":35883,"title":"Corvette K-225","year":"1943","released":"29 Sep 1943","runtime":"98 min","genre":[{"name":"Drama","slug":"drama"},{"name":"War","slug":"war"}],"actors":[{"name":"Randolph Scott","slug":"randolph-scott"},{"name":"James Brown","slug":"james-brown"},{"name":"Ella Raines","slug":"ella-raines"},{"name":"Barry Fitzgerald","slug":"barry-fitzgerald"}],"slug":"corvette-k-225","imageUrl":"att0035757z.jpg","total":3},{"id":32149,"title":"Scarface","year":"1932","released":"09 Apr 1932","runtime":"93 min","genre":[{"name":"Action","slug":"action"},{"name":"Crime","slug":"crime"},{"name":"Drama","slug":"drama"},{"name":"Film-Noir","slug":"film-noir"},{"name":"Thriller","slug":"thriller"}],"actors":[{"name":"Paul Muni","slug":"paul-muni"},{"name":"Ann Dvorak","slug":"ann-dvorak"},{"name":"Karen Morley","slug":"karen-morley"},{"name":"Osgood Perkins","slug":"osgood-perkins"}],"slug":"scarface","imageUrl":"att0023427z.jpg","total":3},{"id":27615,"title":"Come and Get It","year":"1936","released":"23 Dec 1936","runtime":"99 min","genre":[{"name":"Drama","slug":"drama"},{"name":"Romance","slug":"romance"}],"actors":[{"name":"Edward Arnold","slug":"edward-arnold"},{"name":"Joel McCrea","slug":"joel-mccrea"},{"name":"Frances Farmer","slug":"frances-farmer"},{"name":"Walter Brennan","slug":"walter-brennan"}],"slug":"come-and-get-it","imageUrl":"att0027459z.jpg","total":3}]