[{"id":32515,"title":"Ninja: Shadow of a Tear","year":"2013","released":"27 Dec 2013","runtime":"95 min","genre":[{"name":"Action","slug":"action"},{"name":"Thriller","slug":"thriller"}],"actors":[{"name":"Scott Adkins","slug":"scott-adkins"},{"name":"Kane Kosugi","slug":"kane-kosugi"},{"name":"Mika Hijii","slug":"mika-hijii"},{"name":"Markus Waldow","slug":"markus-waldow"}],"slug":"ninja-shadow-of-a-tear","imageUrl":"att2458106z.jpg","total":9},{"id":32416,"title":"Ninja","year":"2009","released":"22 Oct 2009","runtime":"86 min","genre":[{"name":"Action","slug":"action"},{"name":"Thriller","slug":"thriller"}],"actors":[{"name":"Scott Adkins","slug":"scott-adkins"},{"name":"Tsuyoshi Ihara","slug":"tsuyoshi-ihara"},{"name":"Mika Hijii","slug":"mika-hijii"},{"name":"Todd Jensen","slug":"todd-jensen"}],"slug":"ninja","imageUrl":"att1182921z.jpg","total":9},{"id":22612,"title":"The Butcher","year":"2006","released":"11 Jul 2006","runtime":"90 min","genre":[{"name":"Horror","slug":"horror"},{"name":"Thriller","slug":"thriller"}],"actors":[{"name":"Myiea Coy","slug":"myiea-coy"},{"name":"April Gilbert","slug":"april-gilbert"},{"name":"Ashley Rebecca Hawkins","slug":"ashley-rebecca-hawkins"},{"name":"Bill Jacobson","slug":"bill-jacobson"}],"slug":"the-butcher","imageUrl":"att0478165z.jpg","total":9},{"id":21609,"title":"Pumpkinhead: Blood Feud","year":"2007","released":"10 Feb 2007","runtime":"95 min","genre":[{"name":"Fantasy","slug":"fantasy"},{"name":"Horror","slug":"horror"}],"actors":[{"name":"Bob Gunter","slug":"bob-gunter"},{"name":"Amy Manson","slug":"amy-manson"},{"name":"Bradley Taylor","slug":"bradley-taylor"},{"name":"Claire Lams","slug":"claire-lams"}],"slug":"pumpkinhead-blood-feud","imageUrl":"att0790816z.jpg","total":9},{"id":21093,"title":"Re-Kill","year":"2015","released":"16 Oct 2015","runtime":"88 min","genre":[{"name":"Action","slug":"action"},{"name":"Horror","slug":"horror"}],"actors":[{"name":"Bruce Payne","slug":"bruce-payne"},{"name":"Daniella Alonso","slug":"daniella-alonso"},{"name":"Roger Cross","slug":"roger-cross"},{"name":"Scott Adkins","slug":"scott-adkins"}],"slug":"re-kill","imageUrl":"att1612319z.jpg","total":9},{"id":20330,"title":"Room 6","year":"2006","released":"13 Jun 2006","runtime":"94 min","genre":[{"name":"Horror","slug":"horror"},{"name":"Mystery","slug":"mystery"},{"name":"Thriller","slug":"thriller"}],"actors":[{"name":"Christine Taylor","slug":"christine-taylor"},{"name":"Shane Brolly","slug":"shane-brolly"},{"name":"Jerry O'Connell","slug":"jerry-oconnell"},{"name":"Chloë Grace Moretz","slug":"chloe-grace-moretz"}],"slug":"room-6","imageUrl":"att0451187z.jpg","total":9},{"id":13752,"title":"Hardwired","year":"2009","released":"03 Nov 2009","runtime":"94 min","genre":[{"name":"Action","slug":"action"},{"name":"Sci-Fi","slug":"sci-fi"}],"actors":[{"name":"Cuba Gooding Jr.","slug":"cuba-gooding-jr"},{"name":"Val Kilmer","slug":"val-kilmer"},{"name":"Michael Ironside","slug":"michael-ironside"},{"name":"Tatiana Maslany","slug":"tatiana-maslany"}],"slug":"hardwired","imageUrl":"att1405412z.jpg","total":9},{"id":13578,"title":"Paradox","year":"2016","released":"15 Apr 2016","runtime":"90 min","genre":[{"name":"Action","slug":"action"},{"name":"Drama","slug":"drama"},{"name":"Sci-Fi","slug":"sci-fi"}],"actors":[{"name":"Zoë Bell","slug":"zoe-bell"},{"name":"Malik Yoba","slug":"malik-yoba"},{"name":"Adam Huss","slug":"adam-huss"},{"name":"Bjørn Alexander","slug":"bjrn-alexander"}],"slug":"paradox","imageUrl":"att4540434z.jpg","total":9},{"id":13219,"title":"Mansquito","year":"2005","released":"05 Mar 2005","runtime":"92 min","genre":[{"name":"Sci-Fi","slug":"sci-fi"},{"name":"Horror","slug":"horror"}],"actors":[{"name":"Corin Nemec","slug":"corin-nemec"},{"name":"Musetta Vander","slug":"musetta-vander"},{"name":"Matt Jordon","slug":"matt-jordon"},{"name":"Patrick Dreikauss","slug":"patrick-dreikauss"}],"slug":"mansquito","imageUrl":"att0430334z.jpg","total":9}]