[{"id":339,"title":"द ब्लूज़ ब्रदर्स","year":"1980","released":"20 Jun 1980","runtime":"133 min","genre":[{"name":"साहसिक","slug":"adventure"},{"name":"कॉमेडी","slug":"comedy"},{"name":"अपराध","slug":"crime"},{"name":"संगीत","slug":"music"},{"name":"संगीत","slug":"musical"}],"actors":[{"name":"टॉम इरहार्ट","slug":"tom-erhart"},{"name":"जेराल्ड वालिंग","slug":"gerald-walling"},{"name":"जॉन बेलुशी","slug":"john-belushi"},{"name":"वाल्टर लेविन","slug":"walter-levine"}],"slug":"the-blues-brothers","imageUrl":"att0080455z.jpg","total":5843},{"id":334,"title":"बुरे लड़के II","year":"2003","released":"18 Jul 2003","runtime":"147 min","genre":[{"name":"कार्य","slug":"action"},{"name":"कॉमेडी","slug":"comedy"},{"name":"अपराध","slug":"crime"},{"name":"थ्रिलर","slug":"thriller"}],"actors":[{"name":"मार्टिन लॉरेंस","slug":"martin-lawrence"},{"name":"विल स्मिथ","slug":"will-smith"},{"name":"जोर्डी मोल्ला","slug":"jordi-molla"},{"name":"गेब्रियल यूनियन","slug":"gabrielle-union"}],"slug":"bad-boys-ii","imageUrl":"att0172156z.jpg","total":5843},{"id":333,"title":"किंग्समैन: द गोल्डन सर्कल","year":"2017","released":"22 Sep 2017","runtime":"141 min","genre":[{"name":"कार्य","slug":"action"},{"name":"साहसिक","slug":"adventure"},{"name":"कॉमेडी","slug":"comedy"},{"name":"अपराध","slug":"crime"},{"name":"थ्रिलर","slug":"thriller"}],"actors":[{"name":"टेरॉन एगर्टन","slug":"taron-egerton"},{"name":"एडवर्ड होलक्रॉफ्ट","slug":"edward-holcroft"},{"name":"गॉर्डन अलेक्जेंडर","slug":"gordon-alexander"},{"name":"मार्क स्ट्रांग","slug":"mark-strong"}],"slug":"kingsman-the-golden-circle","imageUrl":"att4649466z.jpg","total":5843},{"id":327,"title":"घातक हथियार","year":"2016–2019","released":"21 Sep 2016","runtime":"44 min","genre":[{"name":"कार्य","slug":"action"},{"name":"कॉमेडी","slug":"comedy"},{"name":"अपराध","slug":"crime"},{"name":"नाटक","slug":"drama"},{"name":"थ्रिलर","slug":"thriller"}],"actors":[{"name":"डेमन वेन्स","slug":"damon-wayans"},{"name":"कीशा तेज","slug":"keesha-sharp"},{"name":"केविन रहम","slug":"kevin-rahm"},{"name":"मिशेल मोइन्सर","slug":"michelle-mitchenor"}],"slug":"lethal-weapon","imageUrl":"att5164196z.jpg","total":5843},{"id":323,"title":"पाइनएप्पल एक्सप्रेस","year":"2008","released":"06 Aug 2008","runtime":"111 min","genre":[{"name":"कार्य","slug":"action"},{"name":"कॉमेडी","slug":"comedy"},{"name":"अपराध","slug":"crime"}],"actors":[{"name":"सेठ रोजन","slug":"seth-rogen"},{"name":"जेम्स फ्रेंको","slug":"james-franco"},{"name":"डैनी मैकब्राइड","slug":"danny-mcbride"},{"name":"केविन कोरिगनन","slug":"kevin-corrigan"}],"slug":"pineapple-express","imageUrl":"att0910936z.jpg","total":5843},{"id":319,"title":"द हिटमैन का अंगरक्षक","year":"2017","released":"18 Aug 2017","runtime":"118 min","genre":[{"name":"कार्य","slug":"action"},{"name":"कॉमेडी","slug":"comedy"},{"name":"अपराध","slug":"crime"},{"name":"थ्रिलर","slug":"thriller"}],"actors":[{"name":"एलोडी युंग","slug":"elodie-yung"},{"name":"रेन रेनॉल्ड्स","slug":"ryan-reynolds"},{"name":"त्सुवुकी सौतोम","slug":"tsuwayuki-saotome"},{"name":"रॉय हिल","slug":"roy-hill"}],"slug":"the-hitmans-bodyguard","imageUrl":"att1959563z.jpg","total":5843},{"id":313,"title":"21 जम्प स्ट्रीट","year":"2012","released":"16 Mar 2012","runtime":"109 min","genre":[{"name":"कार्य","slug":"action"},{"name":"कॉमेडी","slug":"comedy"},{"name":"अपराध","slug":"crime"}],"actors":[{"name":"जोनाह हिल","slug":"jonah-hill"},{"name":"चैनिंग टैटम","slug":"channing-tatum"},{"name":"ब्री लार्सन","slug":"brie-larson"},{"name":"डेव फ्रेंको","slug":"dave-franco"}],"slug":"21-jump-street","imageUrl":"att1232829z.jpg","total":5843},{"id":294,"title":"सबसे लंबा अहाता","year":"2005","released":"27 May 2005","runtime":"113 min","genre":[{"name":"कॉमेडी","slug":"comedy"},{"name":"अपराध","slug":"crime"},{"name":"खेल","slug":"sport"}],"actors":[{"name":"एडम सैंडलर","slug":"adam-sandler"},{"name":"क्रिस रॉक","slug":"chris-rock"},{"name":"बर्ट रेनॉल्ड्स","slug":"burt-reynolds"},{"name":"नेल्ली","slug":"nelly"}],"slug":"the-longest-yard","imageUrl":"att0398165z.jpg","total":5843},{"id":269,"title":"जासूस","year":"2015","released":"05 Jun 2015","runtime":"120 min","genre":[{"name":"कार्य","slug":"action"},{"name":"कॉमेडी","slug":"comedy"},{"name":"अपराध","slug":"crime"}],"actors":[{"name":"जूड लॉ","slug":"jude-law"},{"name":"राड रवि","slug":"raad-rawi"},{"name":"मेलिसा मैककार्थी","slug":"melissa-mccarthy"},{"name":"जेसिका चैफिन","slug":"jessica-chaffin"}],"slug":"spy","imageUrl":"att3079380z.jpg","total":5843},{"id":262,"title":"बर्नी में सप्ताहांत","year":"1989","released":"05 Jul 1989","runtime":"97 min","genre":[{"name":"साहसिक","slug":"adventure"},{"name":"कॉमेडी","slug":"comedy"},{"name":"अपराध","slug":"crime"}],"actors":[{"name":"एंड्रयू मैकार्थी","slug":"andrew-mccarthy"},{"name":"जोनाथन सिल्वरमैन","slug":"jonathan-silverman"},{"name":"कैथरीन मैरी स्टीवर्ट","slug":"catherine-mary-stewart"},{"name":"टेरी केसर","slug":"terry-kiser"}],"slug":"weekend-at-bernies","imageUrl":"att0098627z.jpg","total":5843},{"id":261,"title":"iZombie","year":"2015–2019","released":"17 Mar 2015","runtime":"42 min","genre":[{"name":"कॉमेडी","slug":"comedy"},{"name":"अपराध","slug":"crime"},{"name":"नाटक","slug":"drama"},{"name":"डरावनी","slug":"horror"}],"actors":[{"name":"रोज मैकिवर","slug":"rose-mciver"},{"name":"मैल्कम गुडविन","slug":"malcolm-goodwin"},{"name":"राहुल कोहली","slug":"rahul-kohli"},{"name":"रॉबर्ट बकले","slug":"robert-buckley"}],"slug":"izombie","imageUrl":"att3501584z.jpg","total":5843},{"id":242,"title":"महासागर का ११","year":"1960","released":"04 Aug 1960","runtime":"127 min","genre":[{"name":"कॉमेडी","slug":"comedy"},{"name":"अपराध","slug":"crime"},{"name":"संगीत","slug":"music"},{"name":"थ्रिलर","slug":"thriller"}],"actors":[{"name":"फ्रैंक सिनाट्रा","slug":"frank-sinatra"},{"name":"डीन मार्टिन","slug":"dean-martin"},{"name":"सैमी डेविस जूनियर,","slug":"sammy-davis-jr"},{"name":"पीटर लॉफोर्ड","slug":"peter-lawford"}],"slug":"oceans-11","imageUrl":"att0054135z.jpg","total":5843}]