[{"id":597,"title":"Top Places to visit in Bidar, Karnataka","imageUrl":"4212287c-219b-4432-b126-ff6cb21d4433_bidar-railway.jpg","dateCreated":"2019-09-07T02:39:56.465Z","dateModified":"2019-09-07T02:40:09.441Z","contributedBy":"AskGif","content":"Bidar is a hill top city in the north-eastern part of Karnataka state in India. It is the headquarters of the Bidar which borders Maharashtra and Telangana. It is a rapidly urbanising city in the wider Bidar Metropolitan area. The city is well known for its many sites of architectural, historical","ampImage":"https://raw.githubusercontent.com/sumitc91/AmpImage/main/Blogs/4212287c-219b-4432-b126-ff6cb21d4433_bidar-railway.jpg","category":{"name":"travel","slug":"travel"},"tags":[{"name":"bidar","slug":"bidar"},{"name":"karnataka","slug":"karnataka"}],"slug":"top-places-to-visit-in-bidar-karnataka"}]